pm2/__init__.py
pm2/__main__.py
pm2-0.0.4.4.dist-info/LICENSE
pm2-0.0.4.4.dist-info/METADATA
pm2-0.0.4.4.dist-info/WHEEL
pm2-0.0.4.4.dist-info/top_level.txt
pm2-0.0.4.4.dist-info/RECORD
